PdbSublimeTextSupport
