Metadata-Version: 1.0
Name: PdbSublimeTextSupport
Version: 0.2
Summary: Display source code in Sublime Text 2 while debugging with pdb.
Home-page: http://pypi.python.org/pypi/PdbSublimeTextSupport
Author: Martin Aspeli
Author-email: optilude@gmail.com
License: GPL
Keywords: sublimetext pdb
Platform: Mac OS X
Classifier: Development Status :: 4 - Beta
Classifier: Environment :: Console
Classifier: Environment :: MacOS X
Classifier: Intended Audience :: Developers
Classifier: Intended Audience :: System Administrators
Classifier: License :: OSI Approved :: GNU General Public License (GPL)
Classifier: Operating System :: MacOS :: MacOS X
Classifier: Programming Language :: Python
Classifier: Topic :: Software Development :: Debuggers
Classifier: Topic :: Text Editors
